{
  "cert_id": "na2",
  "date": "20040718",
  "label": "2004년 07월 18일",
  "total_questions": 50,
  "questions": [
    {
      "id": "na2_20040718_001",
      "number": 1,
      "subject_id": "tcpip",
      "text": "Windows 2000 Server의 ‘netstat’ 명령 중 Ethernet Interface와 Protocol별 통계결과를 출력하는 명령은?",
      "options": [
        {
          "key": 1,
          "text": "netstat -a -n"
        },
        {
          "key": 2,
          "text": "netstat -e -s"
        },
        {
          "key": 3,
          "text": "netstat -n -s"
        },
        {
          "key": 4,
          "text": "netstat -r -e"
        }
      ],
      "answer": 2,
      "has_figure": false,
      "explanation": {
        "correct_summary": "-e: 이더넷 통계, -s: 프로토콜별 통계",
        "why_correct": "netstat의 -e 옵션은 이더넷 인터페이스 통계(송수신 바이트·패킷·오류)를, -s 옵션은 IP·TCP·UDP·ICMP별 프로토콜 통계를 출력한다. 두 옵션을 결합한 \"netstat -e -s\"가 본 문제의 \"이더넷 인터페이스+프로토콜별 통계\" 정의에 정확히 부합한다.",
        "why_wrong": {
          "1": "-a는 모든 활성 연결과 LISTEN 포트를, -n은 IP/포트를 숫자로 표시하는 옵션입니다. 통계 출력이 아닌 연결 목록 표시이므로 본 문제 정의와 다릅니다.",
          "3": "-n -s 조합은 프로토콜별 통계를 숫자 형식으로 출력하지만, 이더넷 인터페이스 통계(-e)는 포함되지 않습니다. \"이더넷 인터페이스+프로토콜\" 두 항목 모두 만족하지 못합니다.",
          "4": "-r은 라우팅 테이블, -e는 이더넷 통계를 출력합니다. 프로토콜별 통계(-s)가 빠져 있어 본 문제 요구를 절반만 충족하므로 정답이 아닙니다."
        },
        "key_concept": "netstat -e -s",
        "historical_note": "Windows 2000 Server는 2010년 7월 마이크로소프트 지원이 종료된 OS입니다. 본 문항의 옵션·메뉴 구성은 출제 당시 사양이며 현행 운영 환경과는 다를 수 있습니다."
      }
    },
    {
      "id": "na2_20040718_002",
      "number": 2,
      "subject_id": "tcpip",
      "text": "ARP(Address Resolution Protocol)에 관한 설명으로 올바른 것은?",
      "options": [
        {
          "key": 1,
          "text": "데이터 링크 계층에서 이용하는 하드웨어 주소를 IP주소 로 맵핑하는 기능을 제공한다."
        },
        {
          "key": 2,
          "text": "ARP Cache는 IP 주소를 하드웨어 주소로 맵핑한 모든 정보를 유지하고 있다."
        },
        {
          "key": 3,
          "text": "ARP Cache의 내용을 보기 위한 명령으로 arp명령을 이 용하고 이때 옵션은 -a 이다."
        },
        {
          "key": 4,
          "text": "ARP가 IP 주소를 알기 위해 특정 호스트에게 메시지를 전송하고 이에 대한 응답을 기다린다."
        }
      ],
      "answer": 3,
      "has_figure": false,
      "explanation": {
        "correct_summary": "arp -a 명령으로 ARP 캐시 내용 조회",
        "why_correct": "운영체제는 ARP가 학습한 IP-MAC 매핑을 ARP 캐시에 저장하며, arp 명령(arp -a 등)으로 이 캐시 내용을 조회할 수 있다. 사실 그대로의 운용 절차이므로 본 보기가 옳은 설명이다.",
        "why_wrong": {
          "1": "ARP는 IP 주소를 입력으로 하드웨어(MAC) 주소를 알아내는 프로토콜입니다. \"하드웨어 주소를 IP로 변환\"한다는 진술은 RARP의 동작이라 ARP 정의와 정반대입니다.",
          "2": "ARP 캐시는 모든 호스트의 매핑이 아니라 최근 통신한 일부 호스트의 매핑만을 일정 시간 동안 보존합니다. \"모든 매핑\"이라는 단정은 사실과 다릅니다.",
          "4": "ARP는 특정 호스트가 아니라 같은 LAN의 모든 호스트에게 ARP Request를 브로드캐스트해 IP-MAC을 알아냅니다. \"특정 호스트에게 메시지\"라는 진술은 동작 방식과 다릅니다."
        },
        "key_concept": "arp 명령"
      }
    },
    {
      "id": "na2_20040718_003",
      "number": 3,
      "subject_id": "tcpip",
      "text": "TCP/IP 프로토콜 중에서 IP 계층의 한 부분으로 에러 메시지 와 같은 상태 정보를 알려주는 인터넷 제어 메시지 프로토콜 은?",
      "options": [
        {
          "key": 1,
          "text": "ICMP(Internet Control Message Protocol)"
        },
        {
          "key": 2,
          "text": "ARP(Address Resolution Protocol)"
        },
        {
          "key": 3,
          "text": "RARP(Reverse Address Resolution Protocol)"
        },
        {
          "key": 4,
          "text": "UDP(User Datagram Protocol)"
        }
      ],
      "answer": 1,
      "has_figure": false,
      "explanation": {
        "correct_summary": "ICMP는 IP 계층의 오류·진단 메시지 프로토콜",
        "why_correct": "ICMP는 IP 데이터그램에 캡슐화되어 \"Destination Unreachable\", \"Time Exceeded\", \"Echo\" 같은 망 상태·오류 메시지를 라우터·호스트가 주고받게 해 주는 IP 계층 보조 프로토콜이다. 본 문제 정의 그대로다.",
        "why_wrong": {
          "2": "ARP는 IP 주소를 MAC 주소로 매핑하는 프로토콜로, 망 오류 보고가 아니라 주소 해석을 담당합니다. 따라서 본 문제 정의와 다릅니다.",
          "3": "RARP는 MAC 주소로 자신의 IP를 알아내는 부팅용 프로토콜입니다. 망 상태 알림 기능이 아니므로 본 문제 답이 될 수 없습니다.",
          "4": "UDP는 비연결·비신뢰 데이터그램 전송 계층 프로토콜입니다. 응용 데이터 운반용이라 IP 계층의 오류 보고 기능과 다릅니다."
        },
        "key_concept": "ICMP IP 보조"
      }
    },
    {
      "id": "na2_20040718_004",
      "number": 4,
      "subject_id": "tcpip",
      "text": "서버와 클라이언트의 Telnet 프로토콜은 표준안에 정의된 명 령을 주고받으면서 통신을 하는데 이러한 명령은 어떠한 코 드로 구성되어 있는가?",
      "options": [
        {
          "key": 1,
          "text": "EBCDIC"
        },
        {
          "key": 2,
          "text": "ASCII"
        },
        {
          "key": 3,
          "text": "HEXA"
        },
        {
          "key": 4,
          "text": "BINARY"
        }
      ],
      "answer": 2,
      "has_figure": true,
      "explanation": {
        "correct_summary": "Telnet은 NVT(7비트 ASCII) 기반 텍스트 프로토콜",
        "why_correct": "Telnet은 NVT(Network Virtual Terminal) 추상 단말 모델을 사용해 7비트 US-ASCII 코드로 명령과 데이터를 주고받는다. 명령(IAC 0xFF)과 옵션 협상도 ASCII/8비트 옥텟 위에 정의되어 있어 본 문제 정의에 부합한다.",
        "why_wrong": {
          "1": "EBCDIC은 IBM 메인프레임 환경에서 사용되는 8비트 문자 코드 체계입니다. Telnet 표준은 ASCII 기반이라 EBCDIC을 사용하지 않으므로 본 문제 답이 아닙니다.",
          "3": "HEXA(16진수)는 데이터 표기 방식이지 문자 코드 체계가 아닙니다. Telnet 명령의 \"코드\" 분류로는 적합하지 않습니다.",
          "4": "BINARY(이진)은 데이터 표현 형식이지 표준 문자 코드 자체는 아닙니다. Telnet은 ASCII 텍스트를 기본으로 하므로 본 문제 정답이 될 수 없습니다."
        },
        "key_concept": "Telnet ASCII"
      }
    },
    {
      "id": "na2_20040718_005",
      "number": 5,
      "subject_id": "tcpip",
      "text": "A회사에 호스트가 2,500대가 존재한다. 이 경우 B Class 주 소를 할당받게 되면 주소의 낭비가 심하므로 이에 대한 해결 책으로 연속된 C Class를 13개 신청하여 이들을 하나의 네 트워크로 구성하려고 한다. 서브넷의 가장 올바른 설정은?",
      "options": [
        {
          "key": 1,
          "text": "255.255.240.0"
        },
        {
          "key": 2,
          "text": "255.255.255.240"
        },
        {
          "key": 3,
          "text": "255.255.128.0"
        },
        {
          "key": 4,
          "text": "255.255.192.0"
        }
      ],
      "answer": 1,
      "has_figure": false,
      "explanation": {
        "correct_summary": "13개 C Class 묶음 → 16개 단위 슈퍼넷 = /20",
        "why_correct": "연속된 13개의 C Class를 하나로 묶으려면 2⁴=16개를 수용할 수 있는 /20 슈퍼넷 마스크가 필요하다. /20은 255.255.11110000.00000000 = 255.255.240.0이며, 본 문제 요구에 부합하는 슈퍼네팅 마스크다.",
        "why_wrong": {
          "2": "255.255.255.240(/28)은 한 C Class 안에서 16개 호스트씩 16개 서브넷으로 잘게 나누는 마스크입니다. 여러 C Class를 묶는 슈퍼네팅이 아니라 서브네팅이라 본 문제 요구와 정반대입니다.",
          "3": "255.255.128.0(/17)은 호스트 비트를 더 많이 차지해 2⁷=128개의 C Class를 묶는 마스크입니다. 13개에 비해 너무 큰 슈퍼넷이라 효율적이지 않습니다.",
          "4": "255.255.192.0(/18)은 64개의 C Class를 묶는 마스크입니다. 13개를 묶기에는 여전히 과도하게 큰 범위라 본 문제 정답이 아닙니다."
        },
        "key_concept": "슈퍼네팅 13개"
      }
    },
    {
      "id": "na2_20040718_006",
      "number": 6,
      "subject_id": "tcpip",
      "text": "NullMODEM Cable을 이용하여 Windows 98과 Windows 2000 Server를 Windows 98의 ‘케이블 직접연결'을 이용하여 연결하려고 했지만 연결이 되지 않을 때, Windows 2000 Server의 ‘로컬 영역 연결 등록 정보'에서 설치해야 하는 프 로토콜은?",
      "options": [
        {
          "key": 1,
          "text": "NetBEUI"
        },
        {
          "key": 2,
          "text": "NWLink(IPX/SPX)"
        },
        {
          "key": 3,
          "text": "DLC"
        },
        {
          "key": 4,
          "text": "TCP/IP"
        }
      ],
      "answer": 2,
      "has_figure": false,
      "explanation": {
        "correct_summary": "Win98의 직접 연결은 IPX/SPX(NWLink)를 기본 사용",
        "why_correct": "Windows 98의 \"케이블 직접 연결\" 기능은 호스트-게스트 사이에 IPX/SPX 프로토콜로 통신하도록 설계되어 있다. 따라서 Windows 2000 Server 측에 NWLink(IPX/SPX) 호환 프로토콜을 설치해야 양쪽 프로토콜이 일치해 통신이 성립한다.",
        "why_wrong": {
          "1": "NetBEUI는 NetBIOS 위에서 동작하는 비라우팅 LAN 프로토콜로, Windows 98의 직접 연결 기본 프로토콜이 아닙니다. 두 OS의 직접 연결 기본값과 맞지 않습니다.",
          "3": "DLC는 IBM 메인프레임이나 HP 프린터 같은 특수 장비와의 통신용 프로토콜로, PC 간 직접 연결에 사용되지 않습니다. 본 문제 시나리오에 부적합합니다.",
          "4": "TCP/IP로도 직접 연결을 구성할 수 있지만, Windows 98의 \"케이블 직접 연결\" 기본 동작은 IPX/SPX를 사용하므로 가장 즉시 호환되는 답은 NWLink입니다."
        },
        "key_concept": "NWLink IPX/SPX",
        "historical_note": "Windows 2000 Server는 2010년 7월 마이크로소프트 지원이 종료된 OS입니다. 본 문항의 옵션·메뉴 구성은 출제 당시 사양이며 현행 운영 환경과는 다를 수 있습니다."
      }
    },
    {
      "id": "na2_20040718_007",
      "number": 7,
      "subject_id": "tcpip",
      "text": "TCP/IP 4계층에서 인터넷 데이터그램으로 패킷을 캡슐화 하 고 필요한 라우팅 알고리즘의 실행을 담당하는 계층은?",
      "options": [
        {
          "key": 1,
          "text": "Transport Layer"
        },
        {
          "key": 2,
          "text": "Network Interface Layer"
        },
        {
          "key": 3,
          "text": "Internet Layer"
        },
        {
          "key": 4,
          "text": "Application Layer"
        }
      ],
      "answer": 3,
      "has_figure": false,
      "explanation": {
        "correct_summary": "Internet Layer = IP·라우팅 담당",
        "why_correct": "TCP/IP 4계층 모델의 Internet Layer는 IP 헤더를 붙여 패킷을 IP 데이터그램으로 캡슐화하고, 라우팅 테이블·라우팅 프로토콜을 통해 다음 홉을 결정한다. 본 문제 정의에 정확히 부합한다.",
        "why_wrong": {
          "1": "Transport Layer는 TCP·UDP가 위치한 계층으로 종단 간 신뢰성·흐름 제어를 담당합니다. 라우팅이 아니라 종단 통신 제어 영역이므로 본 문제 정의와 다릅니다.",
          "2": "Network Interface Layer(링크 계층)는 매체에 비트·프레임을 송수신하고 MAC 주소 처리를 합니다. IP 라우팅은 그보다 상위인 Internet Layer의 역할이라 본 문제 답이 될 수 없습니다.",
          "4": "Application Layer는 HTTP·FTP·SMTP 같은 사용자 응용 프로토콜이 동작하는 계층입니다. 라우팅이 아니라 서비스 제공 영역이므로 본 문제 정의와 다릅니다."
        },
        "key_concept": "Internet Layer"
      }
    },
    {
      "id": "na2_20040718_008",
      "number": 8,
      "subject_id": "tcpip",
      "text": "IP 주소에 대한 설명으로 가장 올바른 것은?",
      "options": [
        {
          "key": 1,
          "text": "Network ID로 126은 사용할 수 없다."
        },
        {
          "key": 2,
          "text": "Class B의 최상위 2비트는 ‘0’로 설정한다."
        },
        {
          "key": 3,
          "text": "하나의 Network ID에 대해 중복된 Host ID가 존재한다."
        },
        {
          "key": 4,
          "text": "Class C는 주로 소규모 기업의 LAN 환경에 할당된다."
        }
      ],
      "answer": 4,
      "has_figure": false,
      "explanation": {
        "correct_summary": "C Class는 호스트 254개로 소규모 LAN에 적합",
        "why_correct": "C Class는 호스트 ID 8비트로 사용 가능 호스트가 254개이며 네트워크 수가 많아 소규모 기업·기관의 LAN에 분배되었다. 일반적인 운용 관행에 부합하므로 본 보기가 옳은 설명이다.",
        "why_wrong": {
          "1": "Network ID 126(예: 126.0.0.0)은 A Class 영역에 속하는 정상적인 사용 가능 네트워크입니다. \"사용할 수 없다\"는 진술은 사실과 다른 잘못된 설명입니다.",
          "2": "Class B의 최상위 2비트는 \"10\"으로 설정됩니다(0이 아님). \"0\"은 A Class의 최상위 비트이므로 본 보기는 클래스 비트 패턴을 잘못 표기한 설명입니다.",
          "3": "한 네트워크 ID 안에서 호스트 ID는 호스트마다 고유해야 합니다. 중복된 호스트 ID는 IP 충돌을 일으키므로 \"중복이 존재한다\"는 진술은 잘못된 설명입니다."
        },
        "key_concept": "C Class 소규모 LAN"
      }
    },
    {
      "id": "na2_20040718_009",
      "number": 9,
      "subject_id": "tcpip",
      "text": "ARP와 RARP에 대한 설명으로 잘못된 것은?",
      "options": [
        {
          "key": 1,
          "text": "RARP는 브로드캐스팅을 통해 해당 네트워크 주소에 대응 하는 하드웨어의 물리적 주소를 얻는다."
        },
        {
          "key": 2,
          "text": "RARP는 로컬 디스크가 없는 네트워크상에 연결된 시스템 에 사용된다."
        },
        {
          "key": 3,
          "text": "ARP는 중복된 IP 주소 할당을 찾아낸다."
        },
        {
          "key": 4,
          "text": "ARP와 RARP는 IP 주소와 이더넷(Ethernet) 주소를 변환 하는데 관여한다."
        }
      ],
      "answer": 1,
      "has_figure": false,
      "explanation": {
        "correct_summary": "RARP는 자신의 IP를 알아내는 프로토콜(ARP의 반대)",
        "why_correct": "RARP는 호스트가 자신의 MAC을 브로드캐스트해 RARP 서버로부터 자신에게 할당된 IP를 받아오는 프로토콜이다. \"네트워크 주소에 대응되는 MAC을 찾는\" 동작은 ARP의 일이지 RARP의 역할이 아니므로 본 보기는 ARP와 RARP를 혼동한 잘못된 설명이다.",
        "why_wrong": {
          "2": "디스크리스 워크스테이션은 자체 저장소가 없어 부팅 시 RARP를 이용해 자신의 IP를 받아 부팅을 진행합니다. 정의 그대로의 사용 사례이므로 본 문제 정답이 아닙니다.",
          "3": "ARP의 GARP(Gratuitous ARP) 메커니즘으로 자신이 할당받은 IP가 이미 다른 호스트에 의해 사용 중인지 확인할 수 있습니다. IP 중복 검출 기능에 부합하므로 옳은 설명입니다.",
          "4": "ARP는 IP→MAC, RARP는 MAC→IP로 둘 다 IP와 이더넷 MAC 주소 간 매핑을 다룹니다. 두 프로토콜의 공통 동작 영역이라 옳은 설명입니다."
        },
        "key_concept": "RARP 자기 IP 획득"
      }
    },
    {
      "id": "na2_20040718_010",
      "number": 10,
      "subject_id": "tcpip",
      "text": "일반적으로 다른 네트워크와 단 하나의 노드로 연결된 네트 워크를 스터브(Stub) 네트워크라고 한다. 스터브(Stub) 네트 워크를 위한 라우팅 프로토콜로 가장 적합한 것은?",
      "options": [
        {
          "key": 1,
          "text": "스태틱(Static) 라우팅 프로토콜"
        },
        {
          "key": 2,
          "text": "디스턴스 벡터(Distance-Vector) 라우팅 프로토콜"
        },
        {
          "key": 3,
          "text": "링크 스테이트(Link-State) 라우팅 프로토콜"
        },
        {
          "key": 4,
          "text": "딕스트라(Dijkstra) 라우팅 프로토콜"
        }
      ],
      "answer": 1,
      "has_figure": false,
      "explanation": {
        "correct_summary": "스터브망은 출구가 하나뿐이라 정적 라우팅이면 충분",
        "why_correct": "스터브 네트워크는 외부와 연결되는 게이트웨이가 하나뿐이라 동적 라우팅으로 경로를 학습할 필요가 없다. 모든 외부행 트래픽을 그 단일 출구로 보내는 정적(Static) 라우팅으로 간단·안전하게 구성하는 것이 가장 효율적이다.",
        "why_wrong": {
          "2": "Distance-Vector 라우팅(RIP 등)은 다중 경로 환경에서 인접 라우터와 경로 정보를 교환해 최적 경로를 찾는 동적 프로토콜입니다. 출구가 하나뿐인 스터브망에선 오버헤드만 늘어 부적절합니다.",
          "3": "Link-State 라우팅(OSPF 등)도 망 전체 토폴로지를 SPF로 계산하는 동적 프로토콜로, 스터브망에선 불필요한 LSA 트래픽과 자원만 소모됩니다.",
          "4": "다익스트라(Dijkstra)는 OSPF 같은 링크 상태 라우팅의 알고리즘 이름이지 라우팅 프로토콜 그 자체가 아닙니다. 스터브망에 적합한 답으로는 정적 라우팅이 더 정확합니다."
        },
        "key_concept": "스터브망 정적 라우팅"
      }
    },
    {
      "id": "na2_20040718_011",
      "number": 11,
      "subject_id": "tcpip",
      "text": "UDP에 대한 설명으로 올바른 것은?",
      "options": [
        {
          "key": 1,
          "text": "연결형 서비스를 제공한다."
        },
        {
          "key": 2,
          "text": "Telnet은 UDP 상에서 동작한다."
        },
        {
          "key": 3,
          "text": "오류 제어 기능이 없다."
        },
        {
          "key": 4,
          "text": "비교적 안전하게 패킷을 전달하고자 할 때 사용된다."
        }
      ],
      "answer": 3,
      "has_figure": false,
      "explanation": {
        "correct_summary": "UDP는 비신뢰·비연결로 ACK·재전송 같은 오류 제어 부재",
        "why_correct": "UDP는 데이터그램을 보낸 뒤 도달 여부·순서·중복을 확인하지 않는 비신뢰 프로토콜이다. ACK·재전송·시퀀스 번호 같은 오류 제어 메커니즘이 표준에 없으므로 \"오류 제어 기능이 없다\"는 본 보기가 정확한 설명이다.",
        "why_wrong": {
          "1": "연결형 서비스는 3-way handshake로 가상 연결을 설정하는 TCP의 특성입니다. UDP는 비연결 방식이라 본 보기와 정반대입니다.",
          "2": "Telnet은 가상 터미널 세션의 신뢰성 있는 송수신을 위해 TCP 23번 포트로 동작합니다. UDP가 아니므로 본 보기는 사실과 다른 잘못된 설명입니다.",
          "4": "안전한 패킷 전달이 필요할 때는 신뢰성 있는 TCP를 사용합니다. UDP는 오히려 빠른 응답성·저오버헤드가 필요한 서비스(DNS·VoIP)에 사용되므로 본 보기는 부정확합니다."
        },
        "key_concept": "UDP 비신뢰"
      }
    },
    {
      "id": "na2_20040718_012",
      "number": 12,
      "subject_id": "tcpip",
      "text": "TCP/IP 프로토콜에서 IP 계층에서 캡슐화 하여 만들어지는 데이터 단위는?",
      "options": [
        {
          "key": 1,
          "text": "메시지"
        },
        {
          "key": 2,
          "text": "세그먼트"
        },
        {
          "key": 3,
          "text": "데이터그램"
        },
        {
          "key": 4,
          "text": "프레임"
        }
      ],
      "answer": 3,
      "has_figure": false,
      "explanation": {
        "correct_summary": "IP 계층의 PDU는 데이터그램(Datagram)",
        "why_correct": "IP 계층에서 캡슐화된 데이터 단위는 IP 헤더+페이로드로 구성된 \"데이터그램(Datagram)\"이다. RFC 791의 표준 명칭이라 본 문제 정답이다.",
        "why_wrong": {
          "1": "\"메시지\"는 응용 계층의 데이터 단위 명칭으로 사용됩니다. IP 계층 PDU는 아니므로 본 문제 답이 아닙니다.",
          "2": "\"세그먼트\"는 TCP가 캡슐화한 전송 계층 PDU 명칭입니다. IP 계층에서 만들어지는 단위는 아니므로 본 문제 정의와 다릅니다.",
          "4": "\"프레임\"은 데이터링크 계층의 PDU 명칭으로 MAC 헤더+IP 패킷+FCS로 구성됩니다. IP 계층 단위가 아니므로 본 문제 답이 될 수 없습니다."
        },
        "key_concept": "IP 데이터그램"
      }
    },
    {
      "id": "na2_20040718_013",
      "number": 13,
      "subject_id": "tcpip",
      "text": "Class C 에서 유효한 주소는?",
      "options": [
        {
          "key": 1,
          "text": "33.114.17.24"
        },
        {
          "key": 2,
          "text": "128.46.83.25"
        },
        {
          "key": 3,
          "text": "202.67.13.87"
        },
        {
          "key": 4,
          "text": "155.23.94.3"
        }
      ],
      "answer": 3,
      "has_figure": false,
      "explanation": {
        "correct_summary": "첫 옥텟 192~223이면 C Class",
        "why_correct": "IPv4 클래스 분류상 C Class는 첫 옥텟이 192~223 범위로, 상위 비트 110으로 시작한다. 202는 이 범위에 속하므로 202.67.13.87은 C Class 주소다.",
        "why_wrong": {
          "1": "33은 1~126 범위로 A Class에 해당합니다. C Class와 다른 분류이므로 본 문제 답이 될 수 없습니다.",
          "2": "128은 128~191 범위(B Class)에 속합니다. C Class와 다른 클래스이므로 본 문제 답이 아닙니다.",
          "4": "155 또한 128~191 범위로 B Class에 해당합니다. C Class 범위 밖이라 본 문제 답이 아닙니다."
        },
        "key_concept": "C Class 192~223"
      }
    },
    {
      "id": "na2_20040718_014",
      "number": 14,
      "subject_id": "tcpip",
      "text": "TCP/IP에서 Multicast의 의미는?",
      "options": [
        {
          "key": 1,
          "text": "메시지가 한 호스트에서 망상의 특정 그룹 호스트들로 전송하는 것"
        },
        {
          "key": 2,
          "text": "메시지가 한 호스트에서 망상의 다른 모든 호스트들에게 전송하는 것"
        },
        {
          "key": 3,
          "text": "메시지가 한 호스트에서 같은 망에 있는 한 호스트로 전 송하는 것"
        },
        {
          "key": 4,
          "text": "메지시가 한 호스트에서 다른 망에 있는 한 호스트로 전 송하는 것"
        }
      ],
      "answer": 1,
      "has_figure": false,
      "explanation": {
        "correct_summary": "멀티캐스트: 1→다(특정 그룹) 전송",
        "why_correct": "멀티캐스트는 송신측 한 호스트가 \"멀티캐스트 그룹에 가입한 다수 호스트들\"에게 동일 패킷을 한 번에 전달하는 통신 방식이다(IP D Class 224.0.0.0~239.255.255.255 사용). 본 문제 정의에 정확히 부합한다.",
        "why_wrong": {
          "2": "\"망의 모든 호스트에게 전달\"은 브로드캐스트(Broadcast)의 정의입니다. 멀티캐스트는 그룹 멤버에게만 전달되는 점이 다르므로 본 문제 답이 아닙니다.",
          "3": "\"같은 망의 한 호스트에게 전달\"은 유니캐스트(Unicast) 중에서도 LAN 내부 1:1 통신에 해당합니다. 1대N 그룹 통신인 멀티캐스트와 다릅니다.",
          "4": "\"다른 망의 한 호스트에게 전달\" 역시 유니캐스트 라우팅에 해당합니다. 1:1 통신이라 그룹 단위 멀티캐스트와 다른 분류이므로 본 문제 답이 될 수 없습니다."
        },
        "key_concept": "멀티캐스트 그룹"
      }
    },
    {
      "id": "na2_20040718_015",
      "number": 15,
      "subject_id": "tcpip",
      "text": "TCP/IP가 지원하는 링크 계층 프로토콜이 아닌 것은?",
      "options": [
        {
          "key": 1,
          "text": "DQDB"
        },
        {
          "key": 2,
          "text": "RS-232C"
        },
        {
          "key": 3,
          "text": "FDDI"
        },
        {
          "key": 4,
          "text": "Ethernet"
        }
      ],
      "answer": 1,
      "has_figure": false,
      "explanation": {
        "correct_summary": "DQDB는 IEEE 802.6 MAN 표준 — 일반 TCP/IP 링크 계층에 부적합",
        "why_correct": "DQDB(Distributed Queue Dual Bus)는 IEEE 802.6에 정의된 도시 규모 MAN(Metropolitan Area Network) 표준으로, 본 출제 시점의 일반적인 TCP/IP 링크 계층 매체 분류에는 포함되지 않는다. 따라서 \"TCP/IP가 지원하는 링크 계층 프로토콜이 아닌\" 항목으로 정답이다.",
        "why_wrong": {
          "2": "RS-232C는 직렬 회선용 인터페이스 표준으로 PPP·SLIP 등을 통해 TCP/IP가 위에서 동작할 수 있습니다. 표준 링크 계층 매체 분류에 포함되므로 본 문제 정답이 아닙니다.",
          "3": "FDDI(Fiber Distributed Data Interface)는 광 토큰 패싱 LAN 표준으로 TCP/IP가 위에서 동작 가능한 표준 링크 계층입니다. 본 문제 답이 될 수 없습니다.",
          "4": "Ethernet(IEEE 802.3)은 가장 널리 쓰이는 LAN 표준으로 TCP/IP의 대표 링크 계층 매체입니다. 본 문제 정답이 아닙니다."
        },
        "key_concept": "DQDB MAN"
      }
    },
    {
      "id": "na2_20040718_016",
      "number": 16,
      "subject_id": "general",
      "text": "TCP/IP 프로토콜에서 링크 계층의 역할이 아닌 것은?",
      "options": [
        {
          "key": 1,
          "text": "멀티캐스팅을 지원하는 호스트와 라우터에서 사용되는 인터넷 그룹관리"
        },
        {
          "key": 2,
          "text": "RARP 모듈에 대한 RARP 요구/응답의 송수신"
        },
        {
          "key": 3,
          "text": "IP 모듈에 대한 IP 데이터그램의 송수신"
        },
        {
          "key": 4,
          "text": "ARP 모듈에 대한 ARP 요구/응답의 송수신"
        }
      ],
      "answer": 1,
      "has_figure": false,
      "explanation": {
        "correct_summary": "멀티캐스트 그룹 관리는 IGMP의 영역(인터넷 계층)",
        "why_correct": "멀티캐스트 그룹 멤버십 관리는 IGMP가 IP 위에서 처리하는 인터넷 계층의 역할이다. 링크 계층은 프레임의 송수신을 담당하지 멀티캐스트 그룹 관리 자체를 수행하지 않으므로 본 보기는 링크 계층의 역할에 해당하지 않는다.",
        "why_wrong": {
          "2": "RARP 패킷의 실제 송수신(브로드캐스트)은 링크 계층의 프레이밍·MAC 처리에 의해 이루어집니다. 따라서 링크 계층은 RARP 요구/응답 운반을 담당합니다.",
          "3": "링크 계층은 IP 데이터그램을 프레임에 캡슐화해 송수신하는 역할을 합니다. IP 계층에서 받은 패킷을 매체에 실어 전달하는 표준 기능이므로 본 문제 정답이 아닙니다.",
          "4": "ARP 요청/응답 프레임의 실제 송수신도 이더넷·Wi-Fi 같은 링크 계층 매체를 통해 이루어집니다. 링크 계층의 표준 운반 기능에 해당하므로 본 문제 답이 될 수 없습니다."
        },
        "key_concept": "IGMP 인터넷 계층"
      }
    },
    {
      "id": "na2_20040718_017",
      "number": 17,
      "subject_id": "general",
      "text": "TCP에 대한 설명 중 잘못된 것은?",
      "options": [
        {
          "key": 1,
          "text": "Flow Control을 수행한다."
        },
        {
          "key": 2,
          "text": "신뢰할 수 있는 비연결형 프로토콜이다."
        },
        {
          "key": 3,
          "text": "에러 없이 Byte Stream을 전송한다."
        },
        {
          "key": 4,
          "text": "Byte Stream을 일련의 메시지로 쪼개어 Internet 계층에 전달한다."
        }
      ],
      "answer": 2,
      "has_figure": false,
      "explanation": {
        "correct_summary": "TCP는 신뢰성 있는 \"연결지향\" 프로토콜",
        "why_correct": "TCP는 3-way handshake로 가상 연결을 설정한 뒤 시퀀스 번호·ACK·재전송으로 신뢰성 있는 데이터 전달을 보장하는 연결지향(Connection-Oriented) 프로토콜이다. \"비연결형\"이라는 진술은 UDP의 특성과 혼동한 잘못된 설명이라 본 문제 정답이다.",
        "why_wrong": {
          "1": "TCP는 윈도우 크기 기반 흐름 제어로 송수신 측 버퍼 한계에 맞춰 데이터 전송 속도를 조절합니다. 표준 기능이라 옳은 설명이라 정답이 아닙니다.",
          "3": "TCP는 시퀀스 번호와 재전송으로 손실·중복·순서 뒤바뀜을 보정해 응용 계층에는 \"에러 없는\" 연속된 바이트 스트림을 제공합니다. 옳은 설명이라 본 문제 답이 아닙니다.",
          "4": "TCP는 응용이 보낸 바이트 스트림을 MSS 크기에 맞춰 세그먼트로 잘라 IP(Internet) 계층으로 내려보냅니다. 표준 동작이므로 옳은 설명입니다."
        },
        "key_concept": "TCP 연결지향"
      }
    },
    {
      "id": "na2_20040718_018",
      "number": 18,
      "subject_id": "general",
      "text": "8비트의 ASCII코드에서 정보비트는 7비트, 패리티 비트는 1 비트로 하는 비동기식으로 전송하고자 할 때의 전체효율은? (단, 시작 및 정지 비트는 1비트로 하고, 전송 시 문자간격 은 무시한다.)",
      "options": [
        {
          "key": 1,
          "text": "70%"
        },
        {
          "key": 2,
          "text": "80%"
        },
        {
          "key": 3,
          "text": "90%"
        },
        {
          "key": 4,
          "text": "100%"
        }
      ],
      "answer": 1,
      "has_figure": false,
      "explanation": {
        "correct_summary": "효율 = 정보 7bit / 총 10bit = 70%",
        "why_correct": "비동기식 한 문자 프레임은 시작비트 1 + 정보비트 7 + 패리티 1 + 정지비트 1 = 총 10비트이고, 그중 실제 정보는 7비트뿐이다. 7/10 = 0.7 = 70%가 전송 효율이라 본 문제 정답이다.",
        "why_wrong": {
          "2": "80%는 정보 8/총 10비트 같은 다른 가정에서 나오는 효율로, 본 문제 조건(정보 7bit + 패리티 1)과 일치하지 않습니다.",
          "3": "90%는 패리티가 없는 8/총 9비트 같은 가정에서 나올 수 있는 값입니다. 본 문제는 패리티 비트가 포함되므로 적용되지 않습니다.",
          "4": "100%는 시작/정지/패리티 같은 오버헤드 비트가 전혀 없는 이상적 동기 전송에 해당합니다. 비동기 전송에는 오버헤드가 있어 100%일 수 없습니다."
        },
        "key_concept": "비동기 효율 7/10"
      }
    },
    {
      "id": "na2_20040718_019",
      "number": 19,
      "subject_id": "general",
      "text": "Digital전송의 특징이 아닌 것은?",
      "options": [
        {
          "key": 1,
          "text": "데이터 전송 시 Digital 신호를 이용한다."
        },
        {
          "key": 2,
          "text": "신호 재생성기로 증폭기(Amplifier)를 이용한다."
        },
        {
          "key": 3,
          "text": "Analog 전송보다 에러 확률을 감소시킬 수 있다."
        },
        {
          "key": 4,
          "text": "리피터(Repeater)를 거치더라도 잡음까지 신호를 재생성 하지 않는다."
        }
      ],
      "answer": 2,
      "has_figure": false,
      "explanation": {
        "correct_summary": "디지털은 리피터로 비트 재생, 증폭기는 아날로그용",
        "why_correct": "디지털 전송은 신호가 약해졌을 때 리피터(Repeater)로 비트 임계값을 다시 판별해 깨끗한 새 디지털 신호를 \"재생\"한다. 반면 증폭기(Amplifier)는 아날로그 전송에서 신호 자체를 증폭하지만 잡음까지 함께 커지는 특성이 있으므로 \"디지털 전송이 증폭기를 사용한다\"는 진술은 잘못된 설명이다.",
        "why_wrong": {
          "1": "디지털 전송은 0/1 비트열로 인코딩된 디지털 신호를 회선에 실어 보냅니다. 정의 그대로의 사실이라 본 문제 정답이 아닙니다.",
          "3": "디지털 전송은 신호 재생을 통해 누적 잡음을 매번 제거할 수 있어 같은 거리·매체에서 아날로그보다 에러 확률이 낮습니다. 디지털의 대표 장점입니다.",
          "4": "디지털 리피터는 잡음을 함께 증폭하지 않고 비트만 다시 발생시키므로 잡음 누적이 거의 없습니다. 디지털 전송의 핵심 장점이라 옳은 설명입니다."
        },
        "key_concept": "디지털 리피터"
      }
    },
    {
      "id": "na2_20040718_020",
      "number": 20,
      "subject_id": "general",
      "text": "음성 신호를 4KHz의 저역 여파기로 전 처리한 후 PCM전송 을 할 때 표본 주파수는?",
      "options": [
        {
          "key": 1,
          "text": "2KHz"
        },
        {
          "key": 2,
          "text": "4KHz"
        },
        {
          "key": 3,
          "text": "8KHz"
        },
        {
          "key": 4,
          "text": "16KHz"
        }
      ],
      "answer": 3,
      "has_figure": true,
      "explanation": {
        "correct_summary": "나이퀴스트: 최대 4KHz × 2 = 8KHz",
        "why_correct": "나이퀴스트 표본화 정리에 따르면 최대 주파수의 2배 이상으로 표본화해야 신호를 손실 없이 복원할 수 있다. 음성 신호의 최대 주파수가 4KHz로 제한되었으므로 표본 주파수는 8KHz가 되며, 이는 PCM 음성 부호화의 표준 표본화율과 일치한다.",
        "why_wrong": {
          "1": "2KHz는 최대 주파수의 절반에 불과해 나이퀴스트 조건(최대×2)을 충족하지 못합니다. 에일리어싱이 발생해 신호 복원이 불가능합니다.",
          "2": "4KHz는 최대 주파수와 같은 값으로 나이퀴스트 조건(최대×2 이상)에 미달합니다. 정확한 복원이 어려우므로 본 문제 답이 될 수 없습니다.",
          "4": "16KHz는 최대 주파수의 4배로 나이퀴스트 조건은 만족하지만 PCM 음성의 표준 표본화율(8KHz)을 초과합니다. \"손실 없이 복원\"의 표준 답은 8KHz이므로 16KHz는 과도합니다."
        },
        "key_concept": "PCM 8KHz"
      }
    },
    {
      "id": "na2_20040718_021",
      "number": 21,
      "subject_id": "general",
      "text": "데이터 통신 시스템과 외부 환경과의 접속점에 위치하여, 여러 가지 형식으로 표현되는 데이터의 입출력을 위하여 사 용되는 것은?",
      "options": [
        {
          "key": 1,
          "text": "단말장치"
        },
        {
          "key": 2,
          "text": "데이터 전송 회선"
        },
        {
          "key": 3,
          "text": "통신 제어 장치"
        },
        {
          "key": 4,
          "text": "신호 변환 장치"
        }
      ],
      "answer": 1,
      "has_figure": true,
      "explanation": {
        "correct_summary": "단말장치(DTE)는 사용자와 통신 시스템의 접점",
        "why_correct": "단말장치(DTE, Data Terminal Equipment)는 통신 시스템의 종단에 위치해 사용자(외부 환경)와 데이터 통신망을 연결한다. 키보드·디스플레이·프린터 등을 통해 사용자에게 데이터를 입출력하므로 본 문제 정의의 \"외부 환경과 접속점\" 역할에 정확히 부합한다.",
        "why_wrong": {
          "2": "데이터 전송 회선은 두 지점 사이를 잇는 매체(전송로)입니다. 외부와의 접점이 아니라 통신 시스템 내부의 신호 운반 통로이므로 본 문제 정의와 다릅니다.",
          "3": "통신 제어 장치(CCU)는 컴퓨터와 통신 회선 사이의 정합·전송 제어를 담당하는 장비입니다. 사용자 외부 환경과의 직접 접점이 아니라 내부 정합 장치이므로 본 문제 답이 될 수 없습니다.",
          "4": "신호 변환 장치(모뎀·DSU 등)는 신호 형식을 변환해 회선에 적합하게 만드는 장치입니다. 외부 환경과의 입출력 접점이 아니라 신호 처리 장치이므로 본 문제 정의와 다릅니다."
        },
        "key_concept": "DTE 단말장치"
      }
    },
    {
      "id": "na2_20040718_022",
      "number": 22,
      "subject_id": "general",
      "text": "PCM 전송 방식을 올바르게 기술한 것은?",
      "options": [
        {
          "key": 1,
          "text": "음성 -> 표본화 -> 양자화 -> 부호화 -> 전송로"
        },
        {
          "key": 2,
          "text": "음성 -> 양자화 -> 표본화 -> 부호화 -> 전송로"
        },
        {
          "key": 3,
          "text": "음성 -> 표본화 -> 부호화 -> 양자화 -> 전송로"
        },
        {
          "key": 4,
          "text": "음성 -> 양자화 -> 부호화 -> 표본화 -> 전송로"
        }
      ],
      "answer": 1,
      "has_figure": false,
      "explanation": {
        "correct_summary": "PCM = 표본화→양자화→부호화 순서",
        "why_correct": "PCM(Pulse Code Modulation)은 ① 표본화(연속 신호를 일정 시간 간격으로 샘플링) → ② 양자화(샘플 값을 이산 레벨로 근사) → ③ 부호화(이산 레벨을 비트열로 변환) → 전송로 순으로 처리된다. 본 문제 보기 1번이 표준 PCM 절차와 정확히 일치한다.",
        "why_wrong": {
          "2": "양자화→표본화 순서는 PCM의 표준 절차와 어긋납니다. 연속 신호를 먼저 시간축에서 샘플링한 뒤에야 양자화 레벨을 매길 수 있으므로 잘못된 순서입니다.",
          "3": "표본화→부호화→양자화는 비트로 부호화한 뒤 다시 양자화한다는 비논리적 순서입니다. 부호화는 양자화 레벨을 입력으로 받기 때문에 양자화가 먼저여야 합니다.",
          "4": "양자화→부호화→표본화 순서는 처리 흐름이 완전히 뒤바뀐 형태입니다. 시간축 샘플링이 가장 먼저 이뤄져야 하므로 잘못된 순서입니다."
        },
        "key_concept": "PCM 절차"
      }
    },
    {
      "id": "na2_20040718_023",
      "number": 23,
      "subject_id": "general",
      "text": "OSI 7 계층 중, 응용 계층(Application Layer)에서 통신을 수행하는 다양한 정보의 표현 형식을 공통의 전송형식으로 변환하고 암호화 및 압축 등의 기능을 수행하는 계층은?",
      "options": [
        {
          "key": 1,
          "text": "세션 계층"
        },
        {
          "key": 2,
          "text": "네트워크 계층"
        },
        {
          "key": 3,
          "text": "트랜스포트 계층"
        },
        {
          "key": 4,
          "text": "프리젠테이션 계층"
        }
      ],
      "answer": 4,
      "has_figure": true,
      "explanation": {
        "correct_summary": "표현 계층은 형식 변환·암호화·압축 담당",
        "why_correct": "OSI 6계층(표현, Presentation)은 응용 데이터의 표현 형식을 송수신측 모두가 이해할 수 있는 공통 형식(예: ASN.1)으로 변환하고, 암호화·압축 같은 데이터 변환 기능을 수행한다. 본 문제 정의에 정확히 부합한다.",
        "why_wrong": {
          "1": "세션 계층(5)은 응용 간 대화를 시작·관리·종료하고 동기 지점을 두어 복구를 돕는 역할을 합니다. 데이터 형식 변환·암호화는 표현 계층의 일이므로 본 문제 답이 될 수 없습니다.",
          "2": "네트워크 계층(3)은 패킷의 라우팅과 논리 주소 지정을 담당합니다. 형식 변환·암호화와는 다른 영역이라 본 문제 정의와 다릅니다.",
          "3": "트랜스포트 계층(4)은 종단 간 신뢰성·흐름 제어를 담당합니다. 데이터 형식·표현 변환과는 다른 영역이므로 본 문제 답이 아닙니다."
        },
        "key_concept": "표현 계층"
      }
    },
    {
      "id": "na2_20040718_024",
      "number": 24,
      "subject_id": "general",
      "text": "스펙트럼 확산 방식을 이용하여 넓은 주파수 대역에 다수의 사용자가 서로 다른 부호를 사용함으로써 동일한 주파수, 동일한 시간을 사용하여 접속하는 방식은 어떤 원리를 이용 하는 것인가?",
      "options": [
        {
          "key": 1,
          "text": "시분할 다중화"
        },
        {
          "key": 2,
          "text": "코드 분할 다중화"
        },
        {
          "key": 3,
          "text": "주파수 분할 다중화"
        },
        {
          "key": 4,
          "text": "통계적 시분할 다중화"
        }
      ],
      "answer": 2,
      "has_figure": false,
      "explanation": {
        "correct_summary": "CDMA: 사용자별 직교 부호로 동일 시간·주파수 공유",
        "why_correct": "코드 분할 다중화(CDMA)는 스펙트럼 확산 기술로 사용자마다 서로 다른 직교 부호(PN 시퀀스 등)를 곱해 동일한 주파수와 시간 자원을 공유하면서도 수신측이 부호로 신호를 분리할 수 있도록 한다. 본 문제 정의에 정확히 부합한다.",
        "why_wrong": {
          "1": "시분할 다중화(TDM)는 시간 슬롯을 사용자별로 나누어 같은 주파수를 시점이 다르게 공유하는 방식입니다. \"동일한 시간\" 조건과 어긋나므로 본 문제 답이 될 수 없습니다.",
          "3": "주파수 분할 다중화(FDM)는 주파수 대역을 사용자별로 분할해 사용하는 방식입니다. \"동일한 주파수\" 조건과 어긋나므로 본 문제 답이 아닙니다.",
          "4": "통계적 시분할 다중화(STDM)는 활성 사용자에게만 시간 슬롯을 동적 분배하는 TDM의 변형입니다. 시간을 공유하는 점은 같지만 \"동일 시간\"이라는 본 문제 조건에는 부합하지 않습니다."
        },
        "key_concept": "CDMA 부호 분할"
      }
    },
    {
      "id": "na2_20040718_025",
      "number": 25,
      "subject_id": "general",
      "text": "전송매체를 통한 데이터 전송 시 거리가 멀어질수록 신호의 세기가 약해지는 현상은?",
      "options": [
        {
          "key": 1,
          "text": "감쇠현상"
        },
        {
          "key": 2,
          "text": "상호변조잡음"
        },
        {
          "key": 3,
          "text": "지연왜곡"
        },
        {
          "key": 4,
          "text": "누화잡음"
        }
      ],
      "answer": 1,
      "has_figure": false,
      "explanation": {
        "correct_summary": "감쇠(Attenuation)는 거리에 비례한 신호 약화",
        "why_correct": "감쇠(Attenuation)는 전송 매체에서 신호가 진행할수록 매체 저항·흡수 등으로 인해 신호 진폭(세기)이 점차 줄어드는 현상이다. 거리에 비례해 약해지는 본 문제 정의에 정확히 부합한다.",
        "why_wrong": {
          "2": "상호변조잡음은 비선형 시스템에서 둘 이상의 주파수 성분이 합쳐져 새로운 주파수 성분을 만드는 잡음입니다. 거리에 따른 신호 약화와는 다른 현상이므로 본 문제 답이 될 수 없습니다.",
          "3": "지연왜곡은 주파수마다 매체 내 전파 속도가 달라 신호가 변형되는 현상입니다. 진폭 약화가 아니라 도착 시간 차이에 의한 왜곡이라 본 문제 정의와 다릅니다.",
          "4": "누화는 인접 회선의 신호가 다른 회선에 유도되어 잡음으로 끼어드는 결합 잡음입니다. 신호 약화가 아닌 외부 신호 유입이라 본 문제 답이 아닙니다."
        },
        "key_concept": "감쇠"
      }
    },
    {
      "id": "na2_20040718_026",
      "number": 26,
      "subject_id": "general",
      "text": "도시의 여러 부분에 위치한 근거리통신망(LAN)을 상호 연결 최강 자격증 ◑ 전자문제집 CBT : www.comcbt.com 하며, 고속방송망으로 이용되는 것은?",
      "options": [
        {
          "key": 1,
          "text": "FDDI"
        },
        {
          "key": 2,
          "text": "DQDB"
        },
        {
          "key": 3,
          "text": "Ethernet"
        },
        {
          "key": 4,
          "text": "Token Bus"
        }
      ],
      "answer": 2,
      "has_figure": false,
      "explanation": {
        "correct_summary": "DQDB는 IEEE 802.6 MAN 표준 (도시규모)",
        "why_correct": "DQDB(Distributed Queue Dual Bus)는 IEEE 802.6에 표준화된 MAN(Metropolitan Area Network) 기술로, 두 개의 단방향 버스를 사용해 도시 규모의 LAN을 고속으로 상호 연결한다. 본 문제 정의에 정확히 부합한다.",
        "why_wrong": {
          "1": "FDDI는 광 토큰 패싱 LAN/캠퍼스 백본 표준입니다. 도시 규모 MAN까지 확장 가능하긴 하지만 표준 분류상 LAN에 가까우며 본 문제의 정의에는 DQDB가 더 정확합니다.",
          "3": "Ethernet은 LAN(IEEE 802.3) 표준의 통칭입니다. 도시 규모 MAN의 표준 분류는 아니므로 본 문제 정의와 다릅니다.",
          "4": "Token Bus(IEEE 802.4)는 산업용 자동화 환경의 LAN 표준입니다. MAN이 아니라 LAN이므로 본 문제 답이 될 수 없습니다."
        },
        "key_concept": "DQDB MAN"
      }
    },
    {
      "id": "na2_20040718_027",
      "number": 27,
      "subject_id": "general",
      "text": "Token Ring에 대한 설명 중 올바른 것은?",
      "options": [
        {
          "key": 1,
          "text": "DEC에서 개발하였다."
        },
        {
          "key": 2,
          "text": "IEEE802.3 표준안이다."
        },
        {
          "key": 3,
          "text": "충돌이 일어나지 않는다."
        },
        {
          "key": 4,
          "text": "CSMA/CD 방식을 사용하였다."
        }
      ],
      "answer": 3,
      "has_figure": false,
      "explanation": {
        "correct_summary": "토큰을 가진 노드만 송신 → 충돌 원천 차단",
        "why_correct": "Token Ring(IEEE 802.5)은 링 상의 토큰을 점유한 호스트만 데이터를 송신하는 결정적(Deterministic) 매체접근 방식이다. 동시에 둘 이상이 송신할 수 없어 이더넷의 CSMA/CD와 달리 충돌이 원천적으로 발생하지 않으므로 본 보기가 옳다.",
        "why_wrong": {
          "1": "Token Ring은 IBM이 개발해 IEEE 802.5로 표준화한 LAN 기술입니다. DEC가 개발한 것은 DEC Ethernet(이더넷의 초기 변종)이므로 본 보기는 출처를 잘못 표기한 진술입니다.",
          "2": "IEEE 802.3은 CSMA/CD 이더넷 표준이며, Token Ring은 IEEE 802.5에 해당합니다. 표준 번호가 다른 별개 LAN 기술이므로 본 보기는 잘못된 짝짓기입니다.",
          "4": "CSMA/CD는 이더넷의 매체접근 방식입니다. Token Ring은 토큰 기반 결정적 방식을 사용하므로 CSMA/CD를 쓴다는 진술은 토큰링의 정의와 정반대입니다."
        },
        "key_concept": "Token Ring 무충돌"
      }
    },
    {
      "id": "na2_20040718_028",
      "number": 28,
      "subject_id": "nos",
      "text": "LDAP의 설명으로 잘못된 것은?",
      "options": [
        {
          "key": 1,
          "text": "LDAP는 국제표준화를 담당하는 ITU(Internal Telecomm unications Union)에서 디렉터리의 호환을 위해서 만들 었다."
        },
        {
          "key": 2,
          "text": "LDAP 프로토콜은 X.500의 불편한 기능들과 단점들을 배 제한 프로토콜이다."
        },
        {
          "key": 3,
          "text": "LLDAP는 현재 디렉터리 서비스의 표준 프로토콜로 자리 잡고 있다."
        },
        {
          "key": 4,
          "text": "Windows 2000 Server의 Active Directory 서비스는 LDAP 프로토콜을 이용하여 구현되었다."
        }
      ],
      "answer": 1,
      "has_figure": false,
      "explanation": {
        "correct_summary": "LDAP는 ITU가 아닌 IETF가 RFC로 표준화",
        "why_correct": "LDAP(Lightweight Directory Access Protocol)는 IETF가 RFC 4510 등으로 표준화한 디렉터리 액세스 프로토콜이다. ITU는 X.500/X.509 같은 디렉터리·인증서 표준을 담당하지만 LDAP의 표준화 주체는 ITU가 아니므로 본 보기는 잘못된 설명이라 정답이다.",
        "why_wrong": {
          "2": "LDAP는 X.500의 무거운 OSI 기반 DAP(Directory Access Protocol)을 단순화해 TCP/IP 위에서 가볍게 동작하도록 설계되었습니다. \"X.500 단점 배제\"라는 진술은 사실에 부합하는 옳은 설명입니다.",
          "3": "LDAP는 현재 디렉터리 서비스의 사실상 표준 프로토콜로 자리잡았습니다(약간의 오타 \"LLDAP\"가 있지만 내용상은 옳음). Active Directory·OpenLDAP 등 대부분의 디렉터리 서비스가 LDAP를 사용합니다.",
          "4": "Windows 2000 Server의 Active Directory는 LDAP를 표준 액세스 프로토콜로 채택해 동작합니다. 사실에 부합하는 옳은 설명이라 본 문제 정답이 아닙니다."
        },
        "key_concept": "LDAP IETF",
        "historical_note": "Windows 2000 Server는 2010년 7월 마이크로소프트 지원이 종료된 OS입니다. 본 문항의 옵션·메뉴 구성은 출제 당시 사양이며 현행 운영 환경과는 다를 수 있습니다."
      }
    },
    {
      "id": "na2_20040718_029",
      "number": 29,
      "subject_id": "nos",
      "text": "스레드(Thread)에 대한 설명으로 올바른 것은?",
      "options": [
        {
          "key": 1,
          "text": "프로세서의 가장 작은 단위이다."
        },
        {
          "key": 2,
          "text": "시스템에서 실행되고 있는 모든 프로그램을 뜻한다."
        },
        {
          "key": 3,
          "text": "워드나 엑셀 같은 응용 프로그램을 뜻한다."
        },
        {
          "key": 4,
          "text": "동시에 여러 개의 응용 프로그램을 구동할 수 있게 한 다."
        }
      ],
      "answer": 1,
      "has_figure": false,
      "explanation": {
        "correct_summary": "스레드는 프로세스 안의 실행 단위(가장 작은 디스패치 단위)",
        "why_correct": "스레드(Thread)는 프로세스 내부에서 CPU가 실제로 스케줄링·실행하는 가장 작은 단위로, 하나의 프로세스 안에 여러 스레드가 존재해 자원을 공유하며 병렬 실행될 수 있다. 본 보기 \"프로세서의 가장 작은 단위\"라는 일반화된 표현이 이 개념을 가리키는 정답이다.",
        "why_wrong": {
          "2": "시스템에서 실행되는 모든 프로그램을 가리키는 용어는 보통 \"프로세스 집합\"입니다. 스레드는 한 프로세스 안의 실행 단위이지 시스템 전체 프로그램의 집합이 아닙니다.",
          "3": "워드나 엑셀 같은 사용자 응용 프로그램을 가리키는 일반 용어는 \"애플리케이션\"입니다. 스레드는 그 응용 안에서 실행되는 더 작은 실행 단위이므로 본 보기는 잘못된 정의입니다.",
          "4": "여러 응용을 동시에 구동하는 능력은 \"멀티태스킹/멀티프로그래밍\" 개념입니다. 스레드 자체의 정의가 아니라 그것을 활용한 OS 기능 묘사이므로 본 보기는 정답이 될 수 없습니다."
        },
        "key_concept": "스레드 실행 단위"
      }
    },
    {
      "id": "na2_20040718_030",
      "number": 30,
      "subject_id": "nos",
      "text": "Windows 2000 Server의 로컬그룹에 대한 설명으로 올바른 것은?",
      "options": [
        {
          "key": 1,
          "text": "Domain에 속한 모든 컴퓨터에, 로그온이 가능한 계정들 의 그룹이다"
        },
        {
          "key": 2,
          "text": "설치 시 자동으로 생성되어 진다."
        },
        {
          "key": 3,
          "text": "로컬 그룹이 생성되어진 컴퓨터에 있는 자원에 대한 허 가를 위하여 사용한다."
        },
        {
          "key": 4,
          "text": "Windows 2000 Domain Controller에서도 로컬 그룹의 생성이 가능하다."
        }
      ],
      "answer": 3,
      "has_figure": false,
      "explanation": {
        "correct_summary": "로컬 그룹은 그 컴퓨터의 자원에만 권한 적용",
        "why_correct": "로컬 그룹은 그것이 만들어진 컴퓨터의 SAM에 저장되어 그 컴퓨터의 자원(파일·폴더·프린터 등)에 대한 접근 권한을 통제한다. 다른 컴퓨터에는 그 그룹 정의가 영향을 미치지 않으므로 본 보기가 옳은 설명이다.",
        "why_wrong": {
          "1": "도메인의 모든 컴퓨터에 로그온 가능한 계정 묶음은 도메인 사용자/도메인 전역 그룹의 특성에 가깝습니다. 로컬 그룹은 그 컴퓨터에만 한정되므로 본 보기는 다른 그룹 유형과 혼동한 설명입니다.",
          "2": "설치 시 자동 생성되는 항목은 내장 그룹(Administrators·Users·Guests·Power Users 등)으로 일부에 한정됩니다. 사용자가 만든 일반 로컬 그룹은 자동 생성되지 않으므로 본 보기는 일반화가 어렵습니다.",
          "4": "Windows 2000 Domain Controller에서는 SAM이 도메인 디렉터리로 통합되어 일반적인 로컬 그룹 개념이 사라집니다(도메인 로컬 그룹으로 변환). 따라서 \"DC에서도 로컬 그룹\"이라는 진술은 정확하지 않습니다."
        },
        "key_concept": "로컬 그룹 범위",
        "historical_note": "Windows 2000 Server는 2010년 7월 마이크로소프트 지원이 종료된 OS입니다. 본 문항의 옵션·메뉴 구성은 출제 당시 사양이며 현행 운영 환경과는 다를 수 있습니다."
      }
    },
    {
      "id": "na2_20040718_031",
      "number": 31,
      "subject_id": "nos",
      "text": "DHCP 서버에 대한 설명으로 올바른 것은?",
      "options": [
        {
          "key": 1,
          "text": "도메인 이름을 동적으로 IP 주소로 변환하는 일을 담당 하는 서버이다."
        },
        {
          "key": 2,
          "text": "서로 다른 서브넷(Subnet)을 연결하는 역할을 담당한다."
        },
        {
          "key": 3,
          "text": "네트워크에 연결된 컴퓨터에 동적으로 IP 주소를 할당한 다."
        },
        {
          "key": 4,
          "text": "원하는 파일을 찾아 전송하는 역할을 담당한다."
        }
      ],
      "answer": 3,
      "has_figure": false,
      "explanation": {
        "correct_summary": "DHCP는 동적 IP 자동 할당 서비스",
        "why_correct": "DHCP는 클라이언트가 부팅 시 DISCOVER→OFFER→REQUEST→ACK 절차로 IP 주소·서브넷 마스크·기본 게이트웨이·DNS 등을 자동 임대해 주는 서비스다. 본 보기 정의에 정확히 부합한다.",
        "why_wrong": {
          "1": "도메인 이름을 IP로 변환하는 일은 DNS 서버의 역할입니다. DHCP는 IP 분배에 한정되므로 본 보기 정의와 다릅니다.",
          "2": "서로 다른 서브넷을 연결하는 역할은 라우터의 일입니다. DHCP는 클라이언트 IP 자동 분배 서비스라 본 보기 정의와 부합하지 않습니다.",
          "4": "파일을 찾아 전송하는 일은 FTP 같은 파일 전송 프로토콜의 역할입니다. DHCP의 IP 분배 기능과 거리가 멀므로 본 보기 정답이 될 수 없습니다."
        },
        "key_concept": "DHCP IP 분배"
      }
    },
    {
      "id": "na2_20040718_032",
      "number": 32,
      "subject_id": "nos",
      "text": "Windows 2000 Server에서 그룹계정에 대한 설명 중 잘못 된 것은?",
      "options": [
        {
          "key": 1,
          "text": "Users - 포함된 사용자들에게 제한된 권한을 제공"
        },
        {
          "key": 2,
          "text": "Administrators - 시스템에 대한 전체적인 권한을 가짐"
        },
        {
          "key": 3,
          "text": "Guests - 부여된 권한을 수행하거나 허가된 자원에 접 근"
        },
        {
          "key": 4,
          "text": "Replicator - 그룹 맴버들에게 관리 업무를 할 수 있는 제한적 권한을 부여"
        }
      ],
      "answer": 4,
      "has_figure": false,
      "explanation": {
        "correct_summary": "Replicator는 디렉터리 복제 서비스 전용 그룹",
        "why_correct": "Replicator 그룹은 도메인 내 디렉터리 복제(NT 시절 LMRepl) 서비스를 위해 만든 특수 빌트인 그룹으로, 멤버는 일반 사용자가 아니라 복제 서비스 계정으로 한정된다. \"그룹 멤버에게 관리 업무 권한을 부여\"한다는 설명은 사실과 다른 잘못된 정의이므로 정답이다.",
        "why_wrong": {
          "1": "Users 그룹은 일반 사용자 묶음으로 시스템 변경 권한 없이 응용 프로그램 실행과 자기 데이터 접근 정도의 제한된 권한만 받습니다. 표준 빌트인 그룹의 정의에 부합하므로 옳은 설명입니다.",
          "2": "Administrators 그룹은 시스템 전체에 대한 모든 관리 권한을 갖는 빌트인 그룹입니다. 사용자 계정 관리·시스템 설정·서비스 제어 등 모든 작업이 가능하므로 옳은 정의입니다.",
          "3": "Guests 그룹은 임시 사용자에게 매우 제한된 권한을 부여하는 그룹입니다. 부여된 권한 안에서만 자원에 접근할 수 있다는 설명은 표준 동작 그대로이므로 옳은 정의입니다."
        },
        "key_concept": "Replicator 그룹",
        "historical_note": "Windows 2000 Server는 2010년 7월 마이크로소프트 지원이 종료된 OS입니다. 본 문항의 옵션·메뉴 구성은 출제 당시 사양이며 현행 운영 환경과는 다를 수 있습니다."
      }
    },
    {
      "id": "na2_20040718_033",
      "number": 33,
      "subject_id": "nos",
      "text": "NTFS에 대한 설명 중 잘못된 것은?",
      "options": [
        {
          "key": 1,
          "text": "NTFS는 Windows 2000 Server 시스템에서 가장 효율적 인 파일 시스템으로 대부분의 운영체제에서 호환성을 가 진다."
        },
        {
          "key": 2,
          "text": "FAT, HPSF 파일 시스템 보다 더 큰 파일과 파티션 사이 즈를 지원한다."
        },
        {
          "key": 3,
          "text": "FAT와 비교해 볼 때 파일과 디렉터리 단위의 보안을 설 정할 수 있는 이점이 있다."
        },
        {
          "key": 4,
          "text": "파일과 디렉터리의 압축과 POSIX 요구사항을 지원한다."
        }
      ],
      "answer": 1,
      "has_figure": false,
      "explanation": {
        "correct_summary": "NTFS가 \"항상\" 가장 효율적이지는 않음 — 작은 파티션엔 FAT 적합",
        "why_correct": "NTFS는 보안·저널링·압축 등에서 우수하지만 매우 작은 파티션이나 다른 OS와의 호환성, 외부 매체에서는 FAT/FAT32가 더 효율적이거나 호환성 면에서 유리하다. \"가장 효율적\"이라는 절대적 표현은 적합하지 않으므로 본 보기가 옳지 않은 설명이라 정답이다.",
        "why_wrong": {
          "2": "NTFS는 64비트 클러스터 주소를 사용해 이론상 16EB까지의 파일/파티션을 다룰 수 있어 FAT(2~4GB)·HPFS보다 훨씬 큰 파일·파티션을 지원합니다. 사실에 부합하므로 옳은 설명입니다.",
          "3": "NTFS는 파일·폴더마다 ACL을 부여해 사용자/그룹별 권한을 설정할 수 있어 FAT에 비해 보안 기능이 풍부합니다. 사실 그대로의 옳은 설명이라 정답이 아닙니다.",
          "4": "NTFS는 파일/폴더 단위 압축을 표준 기능으로 제공하며 POSIX 호환 하위 시스템에 필요한 하드 링크·대소문자 구분 같은 요구사항도 지원합니다. 옳은 설명입니다."
        },
        "key_concept": "NTFS 절대 효율 X",
        "historical_note": "Windows 2000 Server는 2010년 7월 마이크로소프트 지원이 종료된 OS입니다. 본 문항의 옵션·메뉴 구성은 출제 당시 사양이며 현행 운영 환경과는 다를 수 있습니다."
      }
    },
    {
      "id": "na2_20040718_034",
      "number": 34,
      "subject_id": "nos",
      "text": "Windows 2000 Server를 사용하는 어떤 회사의 DNS에 ‘마 스터 이름서버’와 ‘보조 이름서버’가 설치되어 있을 때, 떨 어진 한 공장에 있는 네트워크 사용자를 위하여 이름해석을 하되 최소한의 대역폭을 사용하는 DNS서버를 구성하고 싶 을 경우 올바른 DNS서버 역할은?",
      "options": [
        {
          "key": 1,
          "text": "마스터 이름 서버"
        },
        {
          "key": 2,
          "text": "보조 이름 서버"
        },
        {
          "key": 3,
          "text": "캐시 서버"
        },
        {
          "key": 4,
          "text": "전달 서버"
        }
      ],
      "answer": 3,
      "has_figure": false,
      "explanation": {
        "correct_summary": "캐시 서버는 영역 데이터 없이 응답을 캐싱만 함",
        "why_correct": "캐시 전용(caching-only) DNS 서버는 자체 영역(zone) 데이터를 보유하지 않고, 클라이언트 질의를 외부 DNS에 위임한 뒤 그 응답을 캐시한다. 영역 전송(Zone Transfer) 트래픽이 없어 원격지에 두기에 가장 가벼운 서버 역할이라 본 문제 \"최소 대역폭\" 요구에 부합한다.",
        "why_wrong": {
          "1": "마스터 이름 서버는 영역 데이터의 원본을 보유하므로 부담이 큰 권한 서버 역할입니다. 원격 공장의 가벼운 이름 해석용으로는 과도한 구성이라 부적합합니다.",
          "2": "보조 이름 서버는 마스터에서 영역 정보를 주기적으로 복제(Zone Transfer)해 옵니다. 본사-공장 사이에 영역 전송 트래픽이 발생해 \"최소 대역폭\" 요구와 어긋납니다.",
          "4": "전달 서버(Forwarder)는 일부 질의를 다른 DNS로 보내는 옵션 구성입니다. 별도 역할이라기보다는 동작 모드이므로, 본 문제처럼 영역 전송 없이 캐시만 운영하는 시나리오의 정답으로는 캐시 서버가 더 정확합니다."
        },
        "key_concept": "Caching-only DNS",
        "historical_note": "Windows 2000 Server는 2010년 7월 마이크로소프트 지원이 종료된 OS입니다. 본 문항의 옵션·메뉴 구성은 출제 당시 사양이며 현행 운영 환경과는 다를 수 있습니다."
      }
    },
    {
      "id": "na2_20040718_035",
      "number": 35,
      "subject_id": "nos",
      "text": "Windows 2000 Server의 WINS 서버에 대한 설명 중 잘못 된 것은?",
      "options": [
        {
          "key": 1,
          "text": "WINS 서버가 실행되는 호스트는 동적 IP 주소를 사용한 다."
        },
        {
          "key": 2,
          "text": "NetBIOS 네트워크 작업을 지원하는 마이크로소프트사의 운영체제가 설치된 로컬네트워크에 사용되는 동적 호스 트 이름 기반의 주소배정 기법이다."
        },
        {
          "key": 3,
          "text": "호스트 이름을 TCP/IP 주소로 맵핑하는 데이터베이스를 유지함으로써 TCP/IP의 모든 장점을 이용하여 쉽게 다른  호스트와 통신할 수 있다."
        },
        {
          "key": 4,
          "text": "많이 요청되는 이름 번역 요청에 대한 브로드캐스트 패 킷을 가로채고 내부에서 처리하여 네트워크의 부하를 줄 일 수 있다."
        }
      ],
      "answer": 1,
      "has_figure": false,
      "explanation": {
        "correct_summary": "WINS 서버 자체는 정적 IP를 사용해야 함",
        "why_correct": "이름 해석 서비스를 제공하는 WINS 서버는 클라이언트가 항상 동일 주소로 찾아갈 수 있어야 하므로 자기 자신은 정적(고정) IP를 사용해야 한다. 따라서 \"WINS 서버 호스트가 동적 IP를 사용한다\"는 진술은 잘못된 설명이라 본 문제 정답이다.",
        "why_wrong": {
          "2": "WINS는 NetBIOS 환경의 이름 해석을 위해 만든 마이크로소프트의 이름 서비스로, NetBIOS 작업을 지원합니다. 정의 그대로의 사실이므로 옳은 설명입니다.",
          "3": "WINS는 NetBIOS 이름과 IP 주소를 매핑한 데이터베이스를 보유해 클라이언트의 질의에 대답합니다. 정의 그대로의 옳은 설명이라 정답이 아닙니다.",
          "4": "WINS는 자주 질의되는 이름을 캐시·등록하므로 클라이언트가 매번 브로드캐스트를 보내지 않아도 됩니다. 브로드캐스트 트래픽 감소가 핵심 이점이므로 옳은 설명입니다."
        },
        "key_concept": "WINS 정적 IP",
        "historical_note": "Windows 2000 Server는 2010년 7월 마이크로소프트 지원이 종료된 OS입니다. 본 문항의 옵션·메뉴 구성은 출제 당시 사양이며 현행 운영 환경과는 다를 수 있습니다."
      }
    },
    {
      "id": "na2_20040718_036",
      "number": 36,
      "subject_id": "nos",
      "text": "Windows 2000 Server에서 ‘로컬보안 설정’의 ‘계정 잠금 정책’ 대화 상자에 포함되지 않는 것은?",
      "options": [
        {
          "key": 1,
          "text": "계정 잠금 기간"
        },
        {
          "key": 2,
          "text": "계정 잠금 임계값"
        },
        {
          "key": 3,
          "text": "다음 시간 후 계정 잠금 수를 원래대로 설정"
        },
        {
          "key": 4,
          "text": "로그온 유지 시간 설정하기"
        }
      ],
      "answer": 4,
      "has_figure": false,
      "explanation": {
        "correct_summary": "계정 잠금 정책은 잠금 기간·임계값·카운터 리셋 3항목",
        "why_correct": "Windows 2000의 로컬 보안 설정 \"계정 잠금 정책\"은 ① 계정 잠금 기간(Lockout duration) ② 계정 잠금 임계값(Lockout threshold) ③ 계정 잠금 수 원래대로 설정(Reset lockout counter after) 세 항목으로 정의된다. \"로그온 유지 시간\"은 별도의 Kerberos 정책 항목에 가까우므로 계정 잠금 정책 대화상자에 포함되지 않는다.",
        "why_wrong": {
          "1": "\"계정 잠금 기간\"은 잠긴 계정을 자동으로 풀어 주기까지의 시간을 정의합니다. 계정 잠금 정책의 표준 항목이므로 본 문제 정답이 아닙니다.",
          "2": "\"계정 잠금 임계값\"은 몇 번의 잘못된 로그온 시도까지 허용한 뒤 계정을 잠글지 결정하는 항목입니다. 표준 항목이라 정답이 될 수 없습니다.",
          "3": "\"다음 시간 후 계정 잠금 수를 원래대로 설정\"은 잘못된 시도 횟수 카운터를 자동 초기화하는 시간을 정의합니다. 계정 잠금 정책의 세 번째 표준 항목입니다."
        },
        "key_concept": "계정 잠금 3항목",
        "historical_note": "Windows 2000 Server는 2010년 7월 마이크로소프트 지원이 종료된 OS입니다. 본 문항의 옵션·메뉴 구성은 출제 당시 사양이며 현행 운영 환경과는 다를 수 있습니다."
      }
    },
    {
      "id": "na2_20040718_037",
      "number": 37,
      "subject_id": "nos",
      "text": "DNS(Domain Name System)서버를 처음 설치하고 가장 먼 저 만들어야 하는 데이터베이스 레코드는?",
      "options": [
        {
          "key": 1,
          "text": "CNAME"
        },
        {
          "key": 2,
          "text": "HINFO(Host Information)"
        },
        {
          "key": 3,
          "text": "PTR(Pointer)"
        },
        {
          "key": 4,
          "text": "SOA(Start Of Authority)"
        }
      ],
      "answer": 4,
      "has_figure": false,
      "explanation": {
        "correct_summary": "SOA 레코드는 영역(Zone)의 권한·설정 정의 — 영역 생성 시 첫 레코드",
        "why_correct": "DNS 영역(Zone)을 만들면 가장 먼저 SOA(Start Of Authority) 레코드가 생성되어 그 영역의 주 네임 서버, 책임자 메일, 시리얼·갱신·재시도·만료·최소 TTL 같은 영역 단위 권한과 동기 정책을 정의한다. 영역의 \"머리\"라 본 문제 정답이다.",
        "why_wrong": {
          "1": "CNAME은 한 호스트 이름이 다른 정식 이름의 별칭임을 나타내는 레코드입니다. 영역 권한 정의가 아닌 별칭 매핑용이라 \"가장 먼저\" 만들 항목은 아닙니다.",
          "2": "HINFO는 호스트의 CPU·OS 등 하드웨어 정보를 저장하는 레코드입니다. 영역 운영의 필수 항목이 아니라 부가 정보용이라 본 문제 답이 될 수 없습니다.",
          "3": "PTR(Pointer)은 IP 주소를 도메인 이름으로 역해석할 때 사용되는 레코드입니다. 역방향 영역 운용에 필요하지만 영역 자체의 권한 정의가 아니므로 \"가장 먼저\"는 SOA가 정확합니다."
        },
        "key_concept": "SOA 레코드"
      }
    },
    {
      "id": "na2_20040718_038",
      "number": 38,
      "subject_id": "nos",
      "text": "Windows 2000 Server의 FTP 서버 기능에 대한 설명 중 올 바른 것은?",
      "options": [
        {
          "key": 1,
          "text": "익명의 사용자가 접근 가능하도록 설정한 경우에는, 다 른 설정 내용과 관계없이 어느 곳에 있는 컴퓨터이든 접 근할 수 있다."
        },
        {
          "key": 2,
          "text": "디렉터리에 대해 실제 디렉터리 이름과 다른 가명을 사 용할 수 있다."
        },
        {
          "key": 3,
          "text": "FTP 서비스를 통해 서버에 접근하는 경우에는 항상 읽 기 권한만이 적용된다."
        },
        {
          "key": 4,
          "text": "모든 디렉터리에 대해 동일한 권한을 설정해야 한다."
        }
      ],
      "answer": 2,
      "has_figure": false,
      "explanation": {
        "correct_summary": "가상 디렉터리로 실제 경로와 다른 \"별칭\" 이름 부여 가능",
        "why_correct": "IIS의 FTP 가상 디렉터리(Virtual Directory) 기능을 사용하면 클라이언트에게 보이는 디렉터리 이름과 서버의 실제 물리 경로를 다르게 매핑할 수 있다. 별칭(Alias) 사용은 표준 기능이므로 본 보기가 옳은 설명이다.",
        "why_wrong": {
          "1": "익명 사용자 접근을 허용해도 다른 인증 방식(기본 인증 등)을 함께 활성화할 수 있습니다. \"익명만 가능\"이라는 식의 단정 진술은 표준 동작과 다르므로 정확하지 않습니다.",
          "3": "FTP 사이트는 디렉터리별로 읽기·쓰기 권한을 따로 설정할 수 있고, 운영자가 쓰기 권한을 부여하면 클라이언트가 업로드도 가능합니다. \"항상 읽기만 가능\"이라는 진술은 사실과 다릅니다.",
          "4": "FTP 사이트의 가상 디렉터리·물리 디렉터리마다 별도의 권한을 설정할 수 있어 일부는 읽기만, 일부는 쓰기까지 허용하는 차등 권한 운용이 가능합니다. \"모두 동일\"이라는 진술은 잘못된 단정입니다."
        },
        "key_concept": "FTP 가상 디렉터리",
        "historical_note": "Windows 2000 Server는 2010년 7월 마이크로소프트 지원이 종료된 OS입니다. 본 문항의 옵션·메뉴 구성은 출제 당시 사양이며 현행 운영 환경과는 다를 수 있습니다."
      }
    },
    {
      "id": "na2_20040718_039",
      "number": 39,
      "subject_id": "equipment",
      "text": "Windows 2000 Server에서 새로운 사용자를 만들어 줄 때 사용자 암호를 사용자만이 알게 하고 싶을 경우 관리자가 설정해야 할 옵션으로 가장 적합한 것은? 최강 자격증 ◑ 전자문제집 CBT : www.comcbt.com",
      "options": [
        {
          "key": 1,
          "text": "?암호 변경할 수 없음"
        },
        {
          "key": 2,
          "text": "?다음 로그온 할 때 반드시 암호 변경"
        },
        {
          "key": 3,
          "text": "?암호 사용 기간 제한 없음"
        },
        {
          "key": 4,
          "text": "?계정 사용 안함"
        }
      ],
      "answer": 2,
      "has_figure": false,
      "explanation": {
        "correct_summary": "첫 로그온 시 암호 강제 변경하면 사용자만 새 암호 알게 됨",
        "why_correct": "관리자가 임시 암호로 계정을 만들어 주고 \"다음 로그온 시 반드시 암호 변경\" 옵션을 활성화하면, 사용자가 첫 로그온 직후 자신만 아는 새 암호로 바꾸게 된다. 이렇게 하면 관리자조차 최종 암호를 알지 못해 \"사용자만이 알게 하기\"라는 본 문제 요구를 충족한다.",
        "why_wrong": {
          "1": "\"암호 변경할 수 없음\" 옵션은 사용자가 임의로 암호를 바꾸지 못하게 막는 정책으로, 관리자가 정한 암호가 그대로 유지됩니다. 사용자만 알게 하는 게 아니라 관리자도 알고 있는 상태이므로 본 요구와 반대입니다.",
          "3": "\"암호 사용 기간 제한 없음\" 옵션은 암호가 만료되지 않도록 설정하는 항목입니다. 누가 암호를 알고 있는지와는 무관한 정책이므로 본 문제 요구와 부합하지 않습니다.",
          "4": "\"계정 사용 안 함\" 옵션은 계정 자체를 비활성화하는 설정입니다. 사용자가 로그인조차 못 하게 만들므로 \"암호를 사용자만 알게\"라는 정상 사용 시나리오와 어긋납니다."
        },
        "key_concept": "첫 로그온 암호 변경",
        "historical_note": "Windows 2000 Server는 2010년 7월 마이크로소프트 지원이 종료된 OS입니다. 본 문항의 옵션·메뉴 구성은 출제 당시 사양이며 현행 운영 환경과는 다를 수 있습니다."
      }
    },
    {
      "id": "na2_20040718_040",
      "number": 40,
      "subject_id": "equipment",
      "text": "Windows 2000 Server 설치 시 기본으로 생성되는 사용자 계정은?",
      "options": [
        {
          "key": 1,
          "text": "Administrator, Guest"
        },
        {
          "key": 2,
          "text": "Administrator, User"
        },
        {
          "key": 3,
          "text": "Power User, Guest"
        },
        {
          "key": 4,
          "text": "Administrator, Power User"
        }
      ],
      "answer": 1,
      "has_figure": false,
      "explanation": {
        "correct_summary": "기본 내장 계정은 Administrator와 Guest 두 개",
        "why_correct": "Windows 2000 Server를 설치하면 SAM/AD에 두 개의 내장(built-in) 계정이 자동으로 만들어진다: Administrator(시스템 관리자, RID 500)와 Guest(임시 사용자, RID 501)다. \"User\"·\"Power User\"는 그룹 명칭이며 기본 계정이 아니므로 정답은 Administrator와 Guest 조합이다.",
        "why_wrong": {
          "2": "\"User\"는 사용자 그룹 이름이지 기본 사용자 계정이 아닙니다. 설치 직후 자동 생성되는 계정 목록에 포함되지 않으므로 Administrator와 짝지어진 본 보기는 잘못된 조합입니다.",
          "3": "\"Power User\"는 그룹 이름이며 기본 계정이 아닙니다. Guest는 기본 계정이 맞으나 Power User가 계정이 아닌 그룹이라 본 조합은 정답이 될 수 없습니다.",
          "4": "Power User 역시 그룹 이름이라 기본 계정 짝짓기로 적절하지 않습니다. 기본 계정 두 개를 가리키는 정확한 조합은 Administrator와 Guest입니다."
        },
        "key_concept": "Windows 내장 계정",
        "historical_note": "Windows 2000 Server는 2010년 7월 마이크로소프트 지원이 종료된 OS입니다. 본 문항의 옵션·메뉴 구성은 출제 당시 사양이며 현행 운영 환경과는 다를 수 있습니다."
      }
    },
    {
      "id": "na2_20040718_041",
      "number": 41,
      "subject_id": "equipment",
      "text": "Windows 2000 Server의 동적 디스크에서 지원하지 않는 볼륨은?",
      "options": [
        {
          "key": 1,
          "text": "단순 볼륨"
        },
        {
          "key": 2,
          "text": "스팬 볼륨"
        },
        {
          "key": 3,
          "text": "RAID - 5 볼륨"
        },
        {
          "key": 4,
          "text": "RAID - 0+1 볼륨"
        }
      ],
      "answer": 4,
      "has_figure": false,
      "explanation": {
        "correct_summary": "Win2K 동적 디스크는 단순·스팬·스트라이프·미러·RAID-5만 지원",
        "why_correct": "Windows 2000 Server의 동적 디스크는 단순(Simple), 스팬(Spanned), 스트라이프(Striped), 미러(Mirrored), RAID-5 볼륨까지 소프트웨어 RAID 차원에서 지원한다. RAID 0+1은 표준 동적 디스크 메뉴에 별도로 등재되지 않으므로 본 문제 정답이다.",
        "why_wrong": {
          "1": "단순 볼륨은 한 디스크 위에 만든 기본 동적 볼륨으로 모든 동적 디스크 환경에서 지원됩니다. 표준 항목이므로 본 문제 정답이 아닙니다.",
          "2": "스팬 볼륨은 여러 디스크를 이어 붙여 큰 볼륨을 만드는 동적 볼륨입니다. RAID는 아니지만 표준 동적 볼륨 유형으로 지원되므로 본 문제 답이 될 수 없습니다.",
          "3": "RAID-5 볼륨은 Windows 2000 Server의 동적 디스크에서 소프트웨어 RAID-5로 표준 지원되는 볼륨 유형입니다. 본 문제 정답이 아닙니다."
        },
        "key_concept": "동적 디스크 볼륨",
        "historical_note": "Windows 2000 Server는 2010년 7월 마이크로소프트 지원이 종료된 OS입니다. 본 문항의 옵션·메뉴 구성은 출제 당시 사양이며 현행 운영 환경과는 다를 수 있습니다."
      }
    },
    {
      "id": "na2_20040718_042",
      "number": 42,
      "subject_id": "equipment",
      "text": "네트워크 인터페이스가 내장된 프린트 디바이스의 사용과 관계가 없는 것은?",
      "options": [
        {
          "key": 1,
          "text": "네트워크 인터페이스 프린트 디바이스는 네트워크에 직 접 연결되므로 IP주소가 할당된다."
        },
        {
          "key": 2,
          "text": "표준(Standard) TCP/IP 프린터 포트를 추가하여 사용할 수 있다."
        },
        {
          "key": 3,
          "text": "로컬 프린터 포트보다 고속 프린팅이 가능하므로 대용량 프린팅 작업에 유리하다."
        },
        {
          "key": 4,
          "text": "네트워크 인터페이스 프린트 디바이스의 포트 이름은 URL 방식으로 입력한다."
        }
      ],
      "answer": 4,
      "has_figure": false,
      "explanation": {
        "correct_summary": "네트워크 프린터 포트 이름은 자유 입력 — 사용 자체와 관계 없음",
        "why_correct": "네트워크 인터페이스 프린터의 \"포트 이름\"은 표준 TCP/IP 포트를 추가할 때 관리자가 임의로 입력하거나 IP 기반 자동 명칭이 부여되는 항목으로, 특정 형식이 강제되거나 프린터 사용에 직접 영향을 주지 않는다. 따라서 본 문제의 \"사용과 관계 없는\" 항목으로 정답이다.",
        "why_wrong": {
          "1": "네트워크 인터페이스 프린터는 PC를 거치지 않고 직접 LAN에 연결되어 자체 IP로 인쇄 작업을 받습니다. 네트워크 직결은 본 장치의 핵심 특성이라 사용과 직접 관계가 있습니다.",
          "2": "Windows에서 네트워크 프린터를 추가할 때 \"표준 TCP/IP 포트\" 마법사로 IP를 지정해 LPR/RAW 프로토콜로 인쇄 큐를 만듭니다. 표준 사용 절차이므로 \"관계 없음\"에 해당하지 않습니다.",
          "3": "네트워크 직결 프린터는 PC의 USB·병렬 포트를 거치지 않으므로 동일 모델 기준으로 더 빠른 처리량을 보여 대용량 인쇄에 유리합니다. 사용 시 장점이라 직접 관련이 있습니다."
        },
        "key_concept": "프린터 포트 이름"
      }
    },
    {
      "id": "na2_20040718_043",
      "number": 43,
      "subject_id": "equipment",
      "text": "호스트 네임과 도메인 네임이 함께 붙여진 이름을 뜻하는 것은?",
      "options": [
        {
          "key": 1,
          "text": "FQDN"
        },
        {
          "key": 2,
          "text": "IP주소"
        },
        {
          "key": 3,
          "text": "가상 주소"
        },
        {
          "key": 4,
          "text": "WINS"
        }
      ],
      "answer": 1,
      "has_figure": false,
      "explanation": {
        "correct_summary": "FQDN은 호스트명+도메인명 전체 표기",
        "why_correct": "FQDN(Fully Qualified Domain Name)은 호스트 이름에 그 호스트가 속한 도메인 이름까지 모두 결합한 완전 식별자다. 예: \"www.comcbt.com\"에서 \"www\"는 호스트, \"comcbt.com\"은 도메인이다. 본 문제 정의(호스트+도메인)에 정확히 일치한다.",
        "why_wrong": {
          "2": "IP 주소는 32비트(IPv4) 또는 128비트(IPv6) 숫자로 표현되는 논리 주소입니다. 사람이 읽는 이름 표기가 아니라 숫자 주소이므로 본 문제 정의와 다릅니다.",
          "3": "\"가상 주소\"는 네트워크 표준 용어가 아니며, 일반적으로 메모리 가상화 등 다른 분야에서 쓰입니다. 호스트+도메인 결합 이름을 가리키는 용어로 사용되지 않습니다.",
          "4": "WINS는 NetBIOS 이름 해석 서비스의 이름이지 호스트+도메인 형태의 이름 표기를 지칭하는 용어가 아닙니다. 서비스명과 명명 규칙은 다른 개념입니다."
        },
        "key_concept": "FQDN"
      }
    },
    {
      "id": "na2_20040718_044",
      "number": 44,
      "subject_id": "equipment",
      "text": "리눅스 설치 시 Swap 영역에 대한 설명 중 잘못된 것은?",
      "options": [
        {
          "key": 1,
          "text": "RAM의 부족한 용량을 보충하기 위해 하드 디스크의 일 정부분을 지정하여 RAM처럼 사용한다."
        },
        {
          "key": 2,
          "text": "일반적으로 실제 메모리의 두 배 정도면 적당하다."
        },
        {
          "key": 3,
          "text": "시스템을 모니터링 한 결과 Swap이 많이 일어나면 메모 리를 증설해야 한다."
        },
        {
          "key": 4,
          "text": "한번 설정한 Swap은 추가가 불가능하므로 신중을 기해 크기를 결정해야 한다."
        }
      ],
      "answer": 4,
      "has_figure": false,
      "explanation": {
        "correct_summary": "Swap은 운영 중에도 추가 가능 (mkswap+swapon)",
        "why_correct": "리눅스 운영 중에도 새 파티션을 만들거나 빈 파일을 dd로 생성한 뒤 mkswap·swapon 명령으로 즉시 추가 swap으로 활성화할 수 있다. 따라서 \"한 번 설정한 Swap은 추가 불가능\"이라는 진술은 사실과 다른 잘못된 설명이라 정답이다.",
        "why_wrong": {
          "1": "Swap 영역은 RAM 부족 시 잘 사용되지 않는 페이지를 디스크로 옮겨 RAM의 부족분을 보충하기 위한 가상 메모리입니다. 정의 그대로의 옳은 설명이라 정답이 아닙니다.",
          "2": "전통적으로 실제 메모리의 1~2배 정도를 Swap 크기로 권장해 왔습니다. 일반적 운용 관행에 부합하므로 옳은 설명입니다(현대 시스템에서는 RAM이 커서 동일 비율 유지가 어렵기도 함).",
          "3": "Swap 사용량이 많다는 것은 RAM이 부족해 자주 디스크-RAM 페이지 교환이 일어남을 의미하므로 RAM 증설이 권장됩니다. 운용 가이드에 부합하는 옳은 설명입니다."
        },
        "key_concept": "Swap 추가 가능"
      }
    },
    {
      "id": "na2_20040718_045",
      "number": 45,
      "subject_id": "equipment",
      "text": "리눅스에서 Disk Quota에 대한 설명 중 올바른 것은?",
      "options": [
        {
          "key": 1,
          "text": "시스템에 사용할 수 있는 디스크의 수를 제한한다."
        },
        {
          "key": 2,
          "text": "User가 특정 파일 시스템에서 사용할 수 있는 디스크의 양을 제한한다."
        },
        {
          "key": 3,
          "text": "User가 특정 디스크에 접속하는 것을 제한한다."
        },
        {
          "key": 4,
          "text": "User가 특정 파일 시스템에 접속하는 것을 제한한다."
        }
      ],
      "answer": 2,
      "has_figure": false,
      "explanation": {
        "correct_summary": "Disk Quota는 사용자별 파일 시스템 사용량 한도",
        "why_correct": "리눅스의 디스크 쿼터(Disk Quota)는 특정 파일 시스템에서 사용자(또는 그룹)가 사용할 수 있는 디스크 용량과 inode 수에 한도를 두어 한 사용자가 디스크를 독점하지 못하도록 제한한다. 본 보기 정의에 정확히 부합한다.",
        "why_wrong": {
          "1": "시스템 전체 디스크의 \"수\"를 제한하는 기능은 표준 OS 차원에서 제공되지 않습니다. 디스크 수가 아니라 사용자별 사용량을 제한하는 것이 쿼터의 본질이므로 본 보기는 잘못된 정의입니다.",
          "3": "Disk Quota는 디스크 접근 자체를 차단하는 기능이 아니라 사용량 한도를 부과하는 기능입니다. 접근 제어는 권한(ACL)·마운트 옵션의 영역이므로 본 보기는 부정확합니다.",
          "4": "파일 시스템에 \"접속\"하는 것을 제한하는 것은 mount/접근 권한 영역의 일입니다. Disk Quota는 사용량 한도 부과이지 접근 자체 제한이 아니므로 본 보기는 잘못된 정의입니다."
        },
        "key_concept": "Disk Quota 사용량"
      }
    },
    {
      "id": "na2_20040718_046",
      "number": 46,
      "subject_id": "equipment",
      "text": "이기종간의 네트워크 특성을 상호 변환하여 호환성이 있는 정보 전송을 가능하게 해주는 기기는?",
      "options": [
        {
          "key": 1,
          "text": "Repeater"
        },
        {
          "key": 2,
          "text": "Bridge"
        },
        {
          "key": 3,
          "text": "Router"
        },
        {
          "key": 4,
          "text": "Gateway"
        }
      ],
      "answer": 4,
      "has_figure": false,
      "explanation": {
        "correct_summary": "Gateway는 이종 프로토콜·아키텍처 변환 장비",
        "why_correct": "게이트웨이는 서로 다른 프로토콜·아키텍처를 갖는 네트워크 사이를 연결하기 위해 필요할 경우 OSI 모든 계층에서 데이터 형식·프로토콜을 변환한다. 이종 시스템 간 호환 통신을 가능하게 해 주므로 본 문제 정의에 정확히 부합한다.",
        "why_wrong": {
          "1": "리피터는 OSI 1계층 장비로 신호 감쇄를 보상해 거리를 확장합니다. 프로토콜 변환 능력이 없어 이종 시스템 연결 정의와 다릅니다.",
          "2": "브리지는 OSI 2계층 장비로 동일 프로토콜의 LAN 세그먼트를 연결합니다. 이종 프로토콜 변환 기능은 없으므로 본 문제 답이 될 수 없습니다.",
          "3": "라우터는 OSI 3계층 장비로 동일 IP 위에서 패킷 라우팅에 한정됩니다. 이종 프로토콜 변환은 게이트웨이의 영역이라 본 문제 답이 아닙니다."
        },
        "key_concept": "Gateway 변환"
      }
    },
    {
      "id": "na2_20040718_047",
      "number": 47,
      "subject_id": "equipment",
      "text": "Star Topology에서 동시에 둘 이상의 Connection이 가능하 며 서로 데이터를 주고받기 위하여 필요한 장치는? 기출문제 전자문제집 CBT : www.comcbt.com 네트워크관리사 2급 ◐ 2004년 07월 18일 필기 기출문제",
      "options": [
        {
          "key": 1,
          "text": "Switching Hub"
        },
        {
          "key": 2,
          "text": "Repeater"
        },
        {
          "key": 3,
          "text": "Hub"
        },
        {
          "key": 4,
          "text": "Bridge"
        }
      ],
      "answer": 1,
      "has_figure": false,
      "explanation": {
        "correct_summary": "스위칭 허브는 포트별 충돌 도메인 분리 → 동시 연결 가능",
        "why_correct": "스위칭 허브는 MAC 주소 학습으로 프레임을 목적 포트로만 전송하고 각 포트에 독립적인 충돌 도메인을 부여한다. 그 결과 여러 쌍의 포트가 동시에 데이터를 주고받을 수 있어 본 문제의 \"동시 둘 이상의 연결\" 요구를 충족한다.",
        "why_wrong": {
          "2": "리피터는 신호 증폭만 하는 1계층 장비로 동시 다중 연결 분리 능력이 없습니다. 모든 신호가 모든 포트로 흘러가므로 본 문제 정의와 다릅니다.",
          "3": "더미 허브(Hub)는 모든 포트가 같은 충돌 도메인을 공유해 한 번에 한 쌍만 통신할 수 있습니다. 동시 다중 연결이 불가능하므로 본 문제 정답이 아닙니다.",
          "4": "브리지는 2계층 장비로 LAN 세그먼트를 분리하지만 일반적으로 2~몇 개 포트 단위입니다. 다포트 동시 연결의 핵심 장비는 스위칭 허브이므로 본 문제 답으로는 스위칭 허브가 더 정확합니다."
        },
        "key_concept": "스위칭 허브"
      }
    },
    {
      "id": "na2_20040718_048",
      "number": 48,
      "subject_id": "equipment",
      "text": "Hub에 대한 설명 중 올바른 것은?",
      "options": [
        {
          "key": 1,
          "text": "Hub에 IP 주소를 배정하지 않아도 통신에는 지장이 없 다."
        },
        {
          "key": 2,
          "text": "네트워크가 서로 다른 두 장비간의 통신에 사용된다."
        },
        {
          "key": 3,
          "text": "필터링 기능으로 다른 포트로 못 건너가게 막아준다."
        },
        {
          "key": 4,
          "text": "콜리전(Collision) 도메인을 나누어 주는 역할을 한다."
        }
      ],
      "answer": 1,
      "has_figure": false,
      "explanation": {
        "correct_summary": "Hub는 OSI 1계층 장비라 IP 주소가 필요 없음",
        "why_correct": "더미 허브는 OSI 1계층(물리)에서 비트 신호를 모든 포트로 흘려 보내는 단순 장비라 자체 IP 주소가 필요 없다(관리 기능이 있는 스마트 허브 제외). IP 없이도 패킷이 정상적으로 통과하므로 본 보기가 옳은 설명이다.",
        "why_wrong": {
          "2": "서로 다른 네트워크의 장비를 연결하는 일은 라우터·게이트웨이의 역할입니다. 허브는 같은 LAN 세그먼트의 단순 집선기이므로 본 보기는 잘못된 정의입니다.",
          "3": "더미 허브에는 필터링 기능이 없습니다. MAC 주소를 인식하지 못하고 들어온 신호를 모든 포트에 그대로 흘리므로 \"포트로 못 건너가게 막는다\"는 진술은 사실과 다릅니다.",
          "4": "충돌 도메인을 나누는 것은 스위치·브리지의 역할입니다. 허브는 모든 포트가 한 충돌 도메인을 공유하므로 본 보기는 사실과 정반대의 잘못된 설명입니다."
        },
        "key_concept": "Hub L1"
      }
    },
    {
      "id": "na2_20040718_049",
      "number": 49,
      "subject_id": "security",
      "text": "광섬유에서 광의 입사각 조건을 표시하는 것은?",
      "options": [
        {
          "key": 1,
          "text": "코어(CORE)"
        },
        {
          "key": 2,
          "text": "클래드(CLAD)"
        },
        {
          "key": 3,
          "text": "모드수(MODE)"
        },
        {
          "key": 4,
          "text": "개구수(NA)"
        }
      ],
      "answer": 4,
      "has_figure": true,
      "explanation": {
        "correct_summary": "개구수(NA)는 광이 광섬유에 입사할 수 있는 최대 각도",
        "why_correct": "개구수(Numerical Aperture, NA)는 광섬유가 받아들일 수 있는 입사각의 한계를 나타내는 매개변수로, NA=sin(θmax)로 정의된다. 코어와 클래드의 굴절률 차이로 결정되며 본 문제의 \"입사각 조건\" 정의에 정확히 부합한다.",
        "why_wrong": {
          "1": "코어(Core)는 광섬유 중앙의 빛이 실제로 진행하는 굴절률이 높은 부분입니다. 광이 흐르는 매체이지 입사각 조건을 표시하는 매개변수는 아닙니다.",
          "2": "클래드(Cladding)는 코어를 감싸는 굴절률이 낮은 외피로, 빛을 코어 안에 가두는 역할을 합니다. 빛이 흐르는 구조 요소이지 입사각 조건 자체를 표시하지는 않습니다.",
          "3": "모드수(Mode)는 광섬유 안에서 빛이 동시에 진행할 수 있는 모드(전파 모드)의 수를 가리킵니다. 단일 모드/다중 모드 분류에 쓰이지만 입사각 조건을 직접 표현하는 매개변수는 아닙니다."
        },
        "key_concept": "개구수 NA"
      }
    },
    {
      "id": "na2_20040718_050",
      "number": 50,
      "subject_id": "security",
      "text": "NetBEUI프로토콜을 사용하는 2개의 개별적인 10BaseT LAN 네트워크를 연결시켜야 한다. 두 LAN을 연결시켜 네트 워크 트래픽을 줄이려할 때 가장 적당한 장치는?",
      "options": [
        {
          "key": 1,
          "text": "Router"
        },
        {
          "key": 2,
          "text": "Bridge"
        },
        {
          "key": 3,
          "text": "Repeater"
        },
        {
          "key": 4,
          "text": "Hub"
        }
      ],
      "answer": 2,
      "has_figure": false,
      "explanation": {
        "correct_summary": "NetBEUI는 라우팅 불가 → 브리지로 연결",
        "why_correct": "NetBEUI는 비라우팅 LAN 프로토콜이라 라우터로 연결할 수 없다. 따라서 두 LAN을 연결하려면 OSI 2계층의 브리지가 적절하다. 브리지는 MAC 주소를 학습해 다른 LAN으로 갈 프레임만 전달하므로 \"트래픽 감소\"라는 요구도 함께 만족시킨다.",
        "why_wrong": {
          "1": "라우터는 IP 같은 라우팅 가능한 프로토콜이 필요합니다. NetBEUI는 라우팅 불가 프로토콜이라 라우터로는 두 LAN 간 NetBEUI 트래픽을 전달할 수 없으므로 본 문제 답이 될 수 없습니다.",
          "3": "리피터는 OSI 1계층 장비로 신호를 모든 포트에 그대로 흘립니다. MAC 주소 학습 능력이 없어 트래픽을 격리하지 못하므로 \"트래픽 감소\" 요구와 부합하지 않습니다.",
          "4": "Hub도 1계층 장비로 모든 포트가 같은 충돌 도메인을 공유합니다. 트래픽 격리 기능이 없어 본 문제 요구를 충족할 수 없으므로 정답이 아닙니다."
        },
        "key_concept": "브리지 NetBEUI",
        "historical_note": "NetBEUI는 Windows 9x/NT 시대의 비라우팅 LAN 프로토콜로 현재는 사용되지 않습니다(Vista부터 OS에서 제거)."
      }
    }
  ]
}